sequin/__init__.py
sequin/client.py
sequin_py-0.1.0.dist-info/LICENSE
sequin_py-0.1.0.dist-info/METADATA
sequin_py-0.1.0.dist-info/WHEEL
sequin_py-0.1.0.dist-info/top_level.txt
sequin_py-0.1.0.dist-info/RECORD
