Metadata-Version: 2.1
Name: sequin-py
Version: 0.1.0
Summary: A Python SDK for Sequin
Home-page: https://github.com/sequinstream/sequin-py
Author: Sequin
Author-email: dev@sequinstream.com
Classifier: Programming Language :: Python :: 3
Classifier: License :: OSI Approved :: MIT License
Classifier: Operating System :: OS Independent
Requires-Python: >=3.6
License-File: LICENSE
Requires-Dist: requests >=2.25.1
